{
  "formatVersion": 1,
  "database": {
    "version": 1,
    "identityHash": "3b344a0d1c25333b336f24c57526853e",
    "entities": [
      {
        "tableName": "tbl_note",
        "createSql": "CREATE TABLE IF NOT EXISTS `${TABLE_NAME}` (`id` INTEGER PRIMARY KEY AUTOINCREMENT NOT NULL, `noteTitle` TEXT NOT NULL, `noteDescription` TEXT NOT NULL)",
        "fields": [
          {
            "fieldPath": "id",
            "columnName": "id",
            "affinity": "INTEGER",
            "notNull": true
          },
          {
            "fieldPath": "noteTitle",
            "columnName": "noteTitle",
            "affinity": "TEXT",
            "notNull": true
          },
          {
            "fieldPath": "noteDescription",
            "columnName": "noteDescription",
            "affinity": "TEXT",
            "notNull": true
          }
        ],
        "primaryKey": {
          "autoGenerate": true,
          "columnNames": [
            "id"
          ]
        },
        "indices": [],
        "foreignKeys": []
      }
    ],
    "views": [],
    "setupQueries": [
      "CREATE TABLE IF NOT EXISTS room_master_table (id INTEGER PRIMARY KEY,identity_hash TEXT)",
      "INSERT OR REPLACE INTO room_master_table (id,identity_hash) VALUES(42, '3b344a0d1c25333b336f24c57526853e')"
    ]
  }
}